LICENSE
MANIFEST.in
README.md
setup.py
max7301/__init__.py
max7301/max7301.py
max7301.egg-info/PKG-INFO
max7301.egg-info/SOURCES.txt
max7301.egg-info/dependency_links.txt
max7301.egg-info/requires.txt
max7301.egg-info/top_level.txt
scripts/py-max7301-rpi-spi-setup